Workbook

Sheet Executive summary
A1: NFI Air Freight Warehouse Model – Executive Summary
A3: Current Baseline Operations (Pre-Launch Model)
A4: Effective Pallet Positions (double-stacked, 65% usable) | B4: ='Virtual Warehouse'!G2 -> 11700
A5: Available Pallet Positions | B5: ='KPI Dashboard'!B4 -> 10380
A6: Realistic Avg Occupancy | B6: ='KPI Dashboard'!B5 -> 0.11282051 | C6: (GREEN - Significant headroom for growth)
A7: Target Daily Inbound Pallets | B7: ='KPI Dashboard'!F3 -> 400
A8: Target Daily Outbound Pallets | B8: ='KPI Dashboard'!F4 -> 380
A9: Total Daily Pallet Moves Required | B9: ='KPI Dashboard'!B8 -> 780
A10: Forklifts Needed (8-hr shift) | B10: ='KPI Dashboard'!B9 -> 4 | C10: Current available: 6 → Covered
A11: Overall Ops Status | B11: ='KPI Dashboard'!B28 -> CRUSHING - Scale up time 🔥
A13: CFS/CES Air Import Batch
A14: Safe Max Sustainable Capacity per Day | B14: ='CFS CES'!B15 -> 122434.78
A15: Labor Cost per kg | B15: ='CFS CES'!B16 -> 0.035266667
A16: Total Labor Cost per Batch | B16: ='CFS CES'!B30 -> 3174
A17: Forklifts Needed per Batch | B17: ='CFS CES'!B24 -> 2
A18: Handling + Storage Revenue per Batch | B18: ='KPI Dashboard'!B18 -> 18000
A20: Outbound Truck Loading Potential (20 dock doors)
A21: Avg Truck Load Time | B21: ='Outbond loading'!B16 -> 20 | C21: Min
A22: Daily Outbound Trucks Potential | B22: ='Outbond loading'!B18 -> 42.5
A23: Daily Outbound Pallets Potential | B23: ='Outbond loading'!B19 -> 765
A25: Growth & Recommendation
A26: Current setup has massive white space: ~89% positions available
A27: Can scale inbound/outbound 3–4x before occupancy/forklift yellow flags
A28: Primary bottleneck at higher volumes: Forklifts (add units as needed)
A29: Use KPI Dashboard tab for real-time what-if scenarios
A30: Model ready for NFI volume forecasts
A34: Creator:
A35: Esteban Conde Medrano - Air Freight Expert
A36: 323-707-0887
A37: estebanconde09@outlook.com

Sheet CFS CES
A1: Air Import Production | E1: Warehouse rate & cost
A2: Total Weight KG | B2: 90000 | C2: KG | E2: Handling fee 0.08 | F2: =(B2*0.08) -> 7200
A3: Rate per Second | B3: 4 | E3: Storage 0.12kg | F3: =B2*0.12 -> 10800
A4: Number of employees | B4: 8
A5: Fatigue/Break factor | B5: 0.15
A7: Time in seconds | B7: =B2*B3 -> 360000
A8: Time in minutes | B8: =B7/60 -> 6000
A9: Time in hours | B9: =B8/60 -> 100
A10: Personal, Fatigue, & Delay | B10: =B8*(1+B5) -> 6900
A11: Time per employee | B11: =B10/B4 -> 862.5
B12: Minutes | C12: hours
A13: Job Completion | B13: =(B2*B3/60)*(1+B5)/B4 -> 862.5 | C13: =B13/60 -> 14.375
A14: Available Production Hours | B14: =8-(40/60) -> 7.3333333
A15: Max Kg sustainable Safe Capacity | B15: =(B14*B4*3600)/(1+$B$5)/1.5 -> 122434.78 | C15: KG
A16: Labor Cost per KG | B16: =+(B30/B2) -> 0.035266667
A17: FORKLIFTS NEEDED FOR THIS BATCH
A18: Pallet weight (KG) | B18: 150
A19: Number of Pallets | B19: =B2/B18 -> 600
A20: Total pallets move | B20: =B19 -> 600
A21: Forklift speed (pallet per hour) | B21: ='Virtual Warehouse'!B17 -> 36
A22: Forklift Hours needed | B22: =B20/B21 -> 16.666667
A23: Job time (hours) | B23: =C13 -> 14.375
A24: Forklift needed | B24: =CEILING(B22/B23,2) -> 2
A27: Average Hourly Rate | B27: 23
A28: Burden 20% | B28: =+B27*1.2 -> 27.6
A29: Total Hours | B29: =+C13*B4 -> 115
A30: Total Labor Cost | B30: =+B29*B28 -> 3174

Sheet Virtual Warehouse
A1: Warehouse Length | B1: Warehouse Width | C1: Usable % | D1: Usable sq ft | E1: Pallet foot print | F1: Double stack | G1: Effective pallet position
A2: 600 | B2: 200 | C2: 0.65 | D2: =(A2*B2*C2) -> 78000 | E2: =(48/12) * (40/12) -> 13.333333 | F2: 2 | G2: =(A2*B2*C2)/E2*F2 -> 11700
A9: Realistic Avg. Occupancy | B9: =B10 / G2 -> 0.11282051
A10: Avg Pallet stored | B10: =B19 * B35 * 1.1 -> 1320
A11: Avaliable position | B11: =G2-B10 -> 10380
A12: Est daily throughput potential | B12: =B37 * 8 * 0.975 -> 252.72
A13: KPI Summary
A14: Avaliable position | B14: =G2-B10 -> 10380
A15: forklift productivity
A16: pallets per forklift per hour | B16: 40
A17: effective pallets/hour (after penalty) | B17: =B16*D17 -> 36 | C17: Efficiency multiplier | D17: 0.9
A18: Daily Shift simulator (8-hr shift)
A19: inbound pallets/day | B19: ='KPI Dashboard'!F3 -> 400
A20: outbound pallets | B20: ='KPI Dashboard'!F4 -> 380
A21: Total pallets moved/day | B21: =B19+B20 -> 780
A22: Required Forklift hours/day | B22: =B21/B17 -> 21.666667
A23: forklifts Needed | B23: =CEILING((B21 / (B37 * 8 * 0.795)), 1) -> 4
A24: Occupancy penalty lookup
A25: Occupancy% | B25: Effiency multiplier
A26: 0 | B26: 1 | C26: Full speed
A27: 0.6 | B27: 0.975 | C27: Tiny slowdown
A28: 0.8 | B28: 0.85 | C28: Noticeable slowdown
A29: 0.85 | B29: 0.6 | C29: Everything crawls
A35: CFS/CES Holds (Days) | B35: 3
A36: CFS/CES Exam/Hold Factor | B36: 0.9
A37: True effective pallets/hr | B37: =(B36*B17) -> 32.4

Sheet Outbond loading
A1: Outbond Truck Loading Simulator
A3: Inputs & Assumptions
A4: Effective pallets per hour | B4: ='Virtual Warehouse'!B17 -> 36
A5: Dedicated Forklift per truck | B5: 1
A6: CFS/CES Buffer (seals,checks,delays) | B6: 0.2
A7: Shift Hours | B7: 8
A8: Dock Doors Available | B8: 20
A10: Truck Scenarios
A11: Truck Type | B11: Pallet Per Truck | C11: Eff.Pallets/hr | D11: Ded. Forklift per truck | E11: Base load Min | F11: Total Est Min | G11: Target SLA Min | H11: Status/Flag
A12: Bobtail/Straight Truck | B12: 12 | C12: ='CFS CES'!$B$21 -> 36 | D12: 1.8 | E12: =(B12 / C12) * 60 / D12 -> 11.111111 | F12: =E12 * (1 + $B$6) -> 13.333333 | G12: 20 | H12: =IF(F12 > G12, "Over Target - Risk", IF(F12 > G12*0.9, "Close - Monitor", "Under/On Target - Good")) -> Under/On Target - Good
A13: 53' Dry Van Trailer | B13: 24 | C13: ='CFS CES'!$B$21 -> 36 | D13: 1.8 | E13: =(B13 / C13) * 60 / D13 -> 22.222222 | F13: =E13 * (1 + $B$6) -> 26.666667 | G13: 35 | H13: =IF(F13 > G13, "Over Target - Risk", IF(F13 > G13*0.9, "Close - Monitor", "Under/On Target - Good")) -> Under/On Target - Good
A15: Bonus Daily KPI
A16: Avg Truck Load time | B16: =AVERAGE(F12:F13) -> 20
A17: Est Trucks per Door per Shift | B17: 20
A18: Total daily outbound trucks | B18: =B8*(B17)*0.85/B7 -> 42.5
A19: Outbond Pallets/day potential | B19: =B18*AVERAGE(B12:B13) -> 765

Sheet KPI Dashboard
A1: Daily Capacity | E1: Quick Inputs
A2: Total effective pallet positions | B2: ='Virtual Warehouse'!G2 -> 11700 | E2: Current forklifts available | F2: 5
A3: Avg pallets currently stored | B3: ='Virtual Warehouse'!B10 -> 1320 | E3: Target daily inbound pallets | F3: 400
A4: Available positions | B4: ='Virtual Warehouse'!B11 -> 10380 | E4: Target daily outbound pallets | F4: 380
A5: Realistic avg occupancy % | B5: ='Virtual Warehouse'!B9 -> 0.11282051 | C5: =IF(B5>F5,"RED - High occupancy","GREEN - Room to grow") -> GREEN - Room to grow | E5: Target occupancy % | F5: 0.6
A6: Daily inbound pallets | B6: =F3 -> 400
A7: Daily outbound pallets | B7: =F4 -> 380
A8: Total daily pallet moves required | B8: =B6+B7 -> 780
A9: Forklifts needed for daily ops (8-hr shift) | B9: ='Virtual Warehouse'!B23 -> 4 | C9: =IF(B9<=F2,"GREEN - Covered","RED - Bottleneck - Need more lifts") -> GREEN - Covered
A10: CFS/CES Batch Performance
A12: Batch weight (kg) | B12: ='CFS CES'!B2 -> 90000
A13: Safe max sustainable kg per day | B13: ='CFS CES'!B15 -> 122434.78
A14: Labor cost per kg | B14: ='CFS CES'!B16 -> 0.035266667
A15: Total labor cost per batch | B15: ='CFS CES'!B30 -> 3174
A16: Forklifts needed per batch | B16: ='CFS CES'!B24 -> 2
A17: Job completion time (hours) | B17: ='CFS CES'!C13 -> 14.375
A18: Handling + Storage revenue per batch | B18: ='CFS CES'!F2 + 'CFS CES'!F3 -> 18000
A19: Outbound Truck Loading Efficiency
A20: Outbound Loading KPIs
A21: Effective pallets per hour (base) | B21: ='Outbond loading'!B4 -> 36
A22: Avg truck load time (min) | B22: ='Outbond loading'!B16 -> 20
A23: Bobtail load time (min) + status | B23: ='Outbond loading'!F12 -> 13.333333 | C23: ='Outbond loading'!H12 -> Under/On Target - Good
A24: 53' Dry Van load time (min) + status | B24: ='Outbond loading'!F13 -> 26.666667 | C24: ='Outbond loading'!H13 -> Under/On Target - Good
A25: Total daily outbound trucks potential | B25: ='Outbond loading'!B18 -> 42.5
A26: Outbound pallets/day potential | B26: ='Outbond loading'!B19 -> 765
A28: Overall Daily Ops Status | B28: =IF(AND(B9<=F2, B5<=F5),"CRUSHING - Scale up time 🔥","CHECK - Forklifts or occupancy risk 😤") -> CRUSHING - Scale up time 🔥
